LICENSE
MANIFEST.in
README.md
setup.cfg
setup.py
TOPSIS_Swapnil_101967003.egg-info/PKG-INFO
TOPSIS_Swapnil_101967003.egg-info/SOURCES.txt
TOPSIS_Swapnil_101967003.egg-info/dependency_links.txt
TOPSIS_Swapnil_101967003.egg-info/entry_points.txt
TOPSIS_Swapnil_101967003.egg-info/requires.txt
TOPSIS_Swapnil_101967003.egg-info/top_level.txt
Topsis_Ranking/102083026.py
Topsis_Ranking/topsis.py