Metadata-Version: 2.1
Name: TOPSIS-Swapnil-101967003
Version: 1.0.4
Summary: A Python package to get best alternative available using TOPSIS method.
Home-page: UNKNOWN
Author: Swapnil Kumar Singh
Author-email: ssingh19_be19@thapar.edu
License: MIT
Platform: UNKNOWN
Classifier: Development Status :: 3 - Alpha
Classifier: Intended Audience :: Developers
Classifier: License :: OSI Approved :: MIT License
Classifier: Programming Language :: Python :: 3
Classifier: Programming Language :: Python :: 3.8
License-File: LICENSE
